{
  "day": 32,
  "title": "Java 17 Records and Sealed Classes",
  "estimatedHours": 3,
  "difficulty": "Intermediate",
  "level": "Intermediate",
  "track": "Mid-Level",
  "tags": [
    "Mid-Level",
    "Intermediate",
    "Phase 4",
    "Interview Prep",
    "Satyverse(Satyam Parmar)"
  ],
  "prerequisites": [
    "Day 31",
    "Day 30"
  ],
  "learningObjectives": [
    "Model immutable data with records and validation",
    "Design sealed hierarchies with explicit permits",
    "Use exhaustive switches safely across variants",
    "Compare records to beans, Lombok, and entities",
    "Plan serialization and API evolution for sealed types",
    "Avoid shallow immutability and framework mismatches"
  ],
  "sections": [
    {
      "type": "why",
      "title": "Why this topic shows up in real interviews",
      "content": "Records and sealed types are the most practical language features for modeling closed sets of data in enterprise Java. They reduce the kilobytes of boilerplate that used to hide bugs in hand-written equals methods, and they give the compiler enough structure to keep switch statements honest when new variants appear.\n\nInterviews increasingly assume you can explain why a record is not a bean with getters and setters, and when immutability is a real guarantee versus a shallow promise because a component still references a mutable collection. That distinction matters in concurrent systems and in caching layers where defensive copies decide correctness.\n\nSealed hierarchies are not only a syntax feature. They are a communication tool: this set of outcomes is complete, and any extension is an explicit design decision. That maps cleanly to payment states, parsing results, and domain events where exhaustive handling is a safety property, not a style preference.\n\nThe combination of records with pattern matching makes business rules easier to read than nested instanceof chains, but it also raises the bar for testing. You need cases for every permitted subtype, and your CI should treat compiler errors as the first line of defense when someone adds a new variant.\n\nFrameworks are still catching up. Persistence, deserialization, and reflection-heavy libraries require explicit configuration for sealed polymorphism. Production maturity means you can describe how you would map these types to JSON or database rows without losing type information at the boundary.\n\nOn call, subtle bugs from mutable components inside immutable-looking records still happen. Your story should include verifying deep immutability, reviewing serialization formats, and ensuring new sealed subtypes did not bypass validation in compact constructors."
    },
    {
      "type": "theory",
      "title": "Java 17 Records and Sealed Classes — theory that sticks",
      "content": "### Plain-language overview\n\n**Records** are transparent carriers for data: immutable components, generated accessors, equals/hashCode/toString, and canonical constructor. **Sealed** types restrict which classes may implement or extend them, enabling **exhaustive** pattern matching.\n\n**Interview angle:** records are not JavaBeans; do not expect setters.\n\n### Record components\n\n| Feature | Behavior |\n| --- | --- |\n| Accessors | name() not getName |\n| Immutability | Final fields |\n| Validation | Compact constructor |\n\n### Sealed class or interface\n\n**permits** lists allowed subclasses; subclasses must be final, sealed, or non-sealed.\n\n### Exhaustive switch\n\nCompiler ensures all permitted subtypes handled—refactor-friendly.\n\n### Serialization\n\nRecords Serializable cautiously—component-wise state.\n\n### Domain modeling\n\nValue objects: Money, Point, IDs—great fit.\n\n### JPA\n\nRecords as entities debated—often DTOs not entities.\n\n### Production angle\n\nUse records for commands/events in clean architectures.\n\n### 60-second story\n\n“I model immutable DTOs with records. I seal hierarchies for closed domains. I rely on exhaustive switches for business rules. I validate in compact constructors. I avoid abusing records for services.”\n\n### Java 17 records and sealed classes — engineering layer 1\n\nUnder delivery pressure, Java backends accumulate quiet technical debt: raw types slipping past code review, streams that allocate more than expected, locks taken in inconsistent order, or modern syntax used without a clear migration story. Layer 1 rehearses how you would detect the regression before it becomes an outage—through JDK-aware CI, structured logs, JFR or async-profiler samples, and tests that assert invariants—not only happy-path compilation. You connect symptoms (Metaspace creep, STW pauses, pool starvation, flaky virtual-thread pinning) back to a language or runtime decision and a fix: clearer APIs, safer concurrency, better defaults, or JVM flags validated with before/after evidence.\n\n**Interview angle:** for layer 1, name one spec-backed guarantee, one metric or dump you would inspect, and one backward-compatible change you would ship first.\n\n### Java 17 records and sealed classes — engineering layer 2\n\nUnder delivery pressure, Java backends accumulate quiet technical debt: raw types slipping past code review, streams that allocate more than expected, locks taken in inconsistent order, or modern syntax used without a clear migration story. Layer 2 rehearses how you would detect the regression before it becomes an outage—through JDK-aware CI, structured logs, JFR or async-profiler samples, and tests that assert invariants—not only happy-path compilation. You connect symptoms (Metaspace creep, STW pauses, pool starvation, flaky virtual-thread pinning) back to a language or runtime decision and a fix: clearer APIs, safer concurrency, better defaults, or JVM flags validated with before/after evidence.\n\n**Interview angle:** for layer 2, name one spec-backed guarantee, one metric or dump you would inspect, and one backward-compatible change you would ship first.\n\n### Java 17 records and sealed classes — engineering layer 3\n\nUnder delivery pressure, Java backends accumulate quiet technical debt: raw types slipping past code review, streams that allocate more than expected, locks taken in inconsistent order, or modern syntax used without a clear migration story. Layer 3 rehearses how you would detect the regression before it becomes an outage—through JDK-aware CI, structured logs, JFR or async-profiler samples, and tests that assert invariants—not only happy-path compilation. You connect symptoms (Metaspace creep, STW pauses, pool starvation, flaky virtual-thread pinning) back to a language or runtime decision and a fix: clearer APIs, safer concurrency, better defaults, or JVM flags validated with before/after evidence.\n\n**Interview angle:** for layer 3, name one spec-backed guarantee, one metric or dump you would inspect, and one backward-compatible change you would ship first.\n\n### Java 17 records and sealed classes — engineering layer 4\n\nUnder delivery pressure, Java backends accumulate quiet technical debt: raw types slipping past code review, streams that allocate more than expected, locks taken in inconsistent order, or modern syntax used without a clear migration story. Layer 4 rehearses how you would detect the regression before it becomes an outage—through JDK-aware CI, structured logs, JFR or async-profiler samples, and tests that assert invariants—not only happy-path compilation. You connect symptoms (Metaspace creep, STW pauses, pool starvation, flaky virtual-thread pinning) back to a language or runtime decision and a fix: clearer APIs, safer concurrency, better defaults, or JVM flags validated with before/after evidence.\n\n**Interview angle:** for layer 4, name one spec-backed guarantee, one metric or dump you would inspect, and one backward-compatible change you would ship first.\n\n### Java 17 records and sealed classes — engineering layer 5\n\nUnder delivery pressure, Java backends accumulate quiet technical debt: raw types slipping past code review, streams that allocate more than expected, locks taken in inconsistent order, or modern syntax used without a clear migration story. Layer 5 rehearses how you would detect the regression before it becomes an outage—through JDK-aware CI, structured logs, JFR or async-profiler samples, and tests that assert invariants—not only happy-path compilation. You connect symptoms (Metaspace creep, STW pauses, pool starvation, flaky virtual-thread pinning) back to a language or runtime decision and a fix: clearer APIs, safer concurrency, better defaults, or JVM flags validated with before/after evidence.\n\n**Interview angle:** for layer 5, name one spec-backed guarantee, one metric or dump you would inspect, and one backward-compatible change you would ship first.\n\n### Java 17 records and sealed classes — engineering layer 6\n\nUnder delivery pressure, Java backends accumulate quiet technical debt: raw types slipping past code review, streams that allocate more than expected, locks taken in inconsistent order, or modern syntax used without a clear migration story. Layer 6 rehearses how you would detect the regression before it becomes an outage—through JDK-aware CI, structured logs, JFR or async-profiler samples, and tests that assert invariants—not only happy-path compilation. You connect symptoms (Metaspace creep, STW pauses, pool starvation, flaky virtual-thread pinning) back to a language or runtime decision and a fix: clearer APIs, safer concurrency, better defaults, or JVM flags validated with before/after evidence.\n\n**Interview angle:** for layer 6, name one spec-backed guarantee, one metric or dump you would inspect, and one backward-compatible change you would ship first.\n\n### Java 17 records and sealed classes — engineering layer 7\n\nUnder delivery pressure, Java backends accumulate quiet technical debt: raw types slipping past code review, streams that allocate more than expected, locks taken in inconsistent order, or modern syntax used without a clear migration story. Layer 7 rehearses how you would detect the regression before it becomes an outage—through JDK-aware CI, structured logs, JFR or async-profiler samples, and tests that assert invariants—not only happy-path compilation. You connect symptoms (Metaspace creep, STW pauses, pool starvation, flaky virtual-thread pinning) back to a language or runtime decision and a fix: clearer APIs, safer concurrency, better defaults, or JVM flags validated with before/after evidence.\n\n**Interview angle:** for layer 7, name one spec-backed guarantee, one metric or dump you would inspect, and one backward-compatible change you would ship first.\n\n### Java 17 records and sealed classes — engineering layer 8\n\nUnder delivery pressure, Java backends accumulate quiet technical debt: raw types slipping past code review, streams that allocate more than expected, locks taken in inconsistent order, or modern syntax used without a clear migration story. Layer 8 rehearses how you would detect the regression before it becomes an outage—through JDK-aware CI, structured logs, JFR or async-profiler samples, and tests that assert invariants—not only happy-path compilation. You connect symptoms (Metaspace creep, STW pauses, pool starvation, flaky virtual-thread pinning) back to a language or runtime decision and a fix: clearer APIs, safer concurrency, better defaults, or JVM flags validated with before/after evidence.\n\n**Interview angle:** for layer 8, name one spec-backed guarantee, one metric or dump you would inspect, and one backward-compatible change you would ship first.\n\n### Java 17 records and sealed classes — engineering layer 9\n\nUnder delivery pressure, Java backends accumulate quiet technical debt: raw types slipping past code review, streams that allocate more than expected, locks taken in inconsistent order, or modern syntax used without a clear migration story. Layer 9 rehearses how you would detect the regression before it becomes an outage—through JDK-aware CI, structured logs, JFR or async-profiler samples, and tests that assert invariants—not only happy-path compilation. You connect symptoms (Metaspace creep, STW pauses, pool starvation, flaky virtual-thread pinning) back to a language or runtime decision and a fix: clearer APIs, safer concurrency, better defaults, or JVM flags validated with before/after evidence.\n\n**Interview angle:** for layer 9, name one spec-backed guarantee, one metric or dump you would inspect, and one backward-compatible change you would ship first.\n\n### Java 17 records and sealed classes — engineering layer 10\n\nUnder delivery pressure, Java backends accumulate quiet technical debt: raw types slipping past code review, streams that allocate more than expected, locks taken in inconsistent order, or modern syntax used without a clear migration story. Layer 10 rehearses how you would detect the regression before it becomes an outage—through JDK-aware CI, structured logs, JFR or async-profiler samples, and tests that assert invariants—not only happy-path compilation. You connect symptoms (Metaspace creep, STW pauses, pool starvation, flaky virtual-thread pinning) back to a language or runtime decision and a fix: clearer APIs, safer concurrency, better defaults, or JVM flags validated with before/after evidence.\n\n**Interview angle:** for layer 10, name one spec-backed guarantee, one metric or dump you would inspect, and one backward-compatible change you would ship first.\n\n### Java 17 records and sealed classes — engineering layer 11\n\nUnder delivery pressure, Java backends accumulate quiet technical debt: raw types slipping past code review, streams that allocate more than expected, locks taken in inconsistent order, or modern syntax used without a clear migration story. Layer 11 rehearses how you would detect the regression before it becomes an outage—through JDK-aware CI, structured logs, JFR or async-profiler samples, and tests that assert invariants—not only happy-path compilation. You connect symptoms (Metaspace creep, STW pauses, pool starvation, flaky virtual-thread pinning) back to a language or runtime decision and a fix: clearer APIs, safer concurrency, better defaults, or JVM flags validated with before/after evidence.\n\n**Interview angle:** for layer 11, name one spec-backed guarantee, one metric or dump you would inspect, and one backward-compatible change you would ship first.\n\n### Java 17 records and sealed classes — engineering layer 12\n\nUnder delivery pressure, Java backends accumulate quiet technical debt: raw types slipping past code review, streams that allocate more than expected, locks taken in inconsistent order, or modern syntax used without a clear migration story. Layer 12 rehearses how you would detect the regression before it becomes an outage—through JDK-aware CI, structured logs, JFR or async-profiler samples, and tests that assert invariants—not only happy-path compilation. You connect symptoms (Metaspace creep, STW pauses, pool starvation, flaky virtual-thread pinning) back to a language or runtime decision and a fix: clearer APIs, safer concurrency, better defaults, or JVM flags validated with before/after evidence.\n\n**Interview angle:** for layer 12, name one spec-backed guarantee, one metric or dump you would inspect, and one backward-compatible change you would ship first.\n\n### Java 17 records and sealed classes — engineering layer 13\n\nUnder delivery pressure, Java backends accumulate quiet technical debt: raw types slipping past code review, streams that allocate more than expected, locks taken in inconsistent order, or modern syntax used without a clear migration story. Layer 13 rehearses how you would detect the regression before it becomes an outage—through JDK-aware CI, structured logs, JFR or async-profiler samples, and tests that assert invariants—not only happy-path compilation. You connect symptoms (Metaspace creep, STW pauses, pool starvation, flaky virtual-thread pinning) back to a language or runtime decision and a fix: clearer APIs, safer concurrency, better defaults, or JVM flags validated with before/after evidence.\n\n**Interview angle:** for layer 13, name one spec-backed guarantee, one metric or dump you would inspect, and one backward-compatible change you would ship first.\n\n### Java 17 records and sealed classes — engineering layer 14\n\nUnder delivery pressure, Java backends accumulate quiet technical debt: raw types slipping past code review, streams that allocate more than expected, locks taken in inconsistent order, or modern syntax used without a clear migration story. Layer 14 rehearses how you would detect the regression before it becomes an outage—through JDK-aware CI, structured logs, JFR or async-profiler samples, and tests that assert invariants—not only happy-path compilation. You connect symptoms (Metaspace creep, STW pauses, pool starvation, flaky virtual-thread pinning) back to a language or runtime decision and a fix: clearer APIs, safer concurrency, better defaults, or JVM flags validated with before/after evidence.\n\n**Interview angle:** for layer 14, name one spec-backed guarantee, one metric or dump you would inspect, and one backward-compatible change you would ship first.\n\n### Java 17 records and sealed classes — engineering layer 15\n\nUnder delivery pressure, Java backends accumulate quiet technical debt: raw types slipping past code review, streams that allocate more than expected, locks taken in inconsistent order, or modern syntax used without a clear migration story. Layer 15 rehearses how you would detect the regression before it becomes an outage—through JDK-aware CI, structured logs, JFR or async-profiler samples, and tests that assert invariants—not only happy-path compilation. You connect symptoms (Metaspace creep, STW pauses, pool starvation, flaky virtual-thread pinning) back to a language or runtime decision and a fix: clearer APIs, safer concurrency, better defaults, or JVM flags validated with before/after evidence.\n\n**Interview angle:** for layer 15, name one spec-backed guarantee, one metric or dump you would inspect, and one backward-compatible change you would ship first.\n\n### Java 17 records and sealed classes — engineering layer 16\n\nUnder delivery pressure, Java backends accumulate quiet technical debt: raw types slipping past code review, streams that allocate more than expected, locks taken in inconsistent order, or modern syntax used without a clear migration story. Layer 16 rehearses how you would detect the regression before it becomes an outage—through JDK-aware CI, structured logs, JFR or async-profiler samples, and tests that assert invariants—not only happy-path compilation. You connect symptoms (Metaspace creep, STW pauses, pool starvation, flaky virtual-thread pinning) back to a language or runtime decision and a fix: clearer APIs, safer concurrency, better defaults, or JVM flags validated with before/after evidence.\n\n**Interview angle:** for layer 16, name one spec-backed guarantee, one metric or dump you would inspect, and one backward-compatible change you would ship first.\n\n### Java 17 records and sealed classes — engineering layer 17\n\nUnder delivery pressure, Java backends accumulate quiet technical debt: raw types slipping past code review, streams that allocate more than expected, locks taken in inconsistent order, or modern syntax used without a clear migration story. Layer 17 rehearses how you would detect the regression before it becomes an outage—through JDK-aware CI, structured logs, JFR or async-profiler samples, and tests that assert invariants—not only happy-path compilation. You connect symptoms (Metaspace creep, STW pauses, pool starvation, flaky virtual-thread pinning) back to a language or runtime decision and a fix: clearer APIs, safer concurrency, better defaults, or JVM flags validated with before/after evidence.\n\n**Interview angle:** for layer 17, name one spec-backed guarantee, one metric or dump you would inspect, and one backward-compatible change you would ship first.\n\n### Java 17 records and sealed classes — engineering layer 18\n\nUnder delivery pressure, Java backends accumulate quiet technical debt: raw types slipping past code review, streams that allocate more than expected, locks taken in inconsistent order, or modern syntax used without a clear migration story. Layer 18 rehearses how you would detect the regression before it becomes an outage—through JDK-aware CI, structured logs, JFR or async-profiler samples, and tests that assert invariants—not only happy-path compilation. You connect symptoms (Metaspace creep, STW pauses, pool starvation, flaky virtual-thread pinning) back to a language or runtime decision and a fix: clearer APIs, safer concurrency, better defaults, or JVM flags validated with before/after evidence.\n\n**Interview angle:** for layer 18, name one spec-backed guarantee, one metric or dump you would inspect, and one backward-compatible change you would ship first.\n\n### Java 17 records and sealed classes — engineering layer 19\n\nUnder delivery pressure, Java backends accumulate quiet technical debt: raw types slipping past code review, streams that allocate more than expected, locks taken in inconsistent order, or modern syntax used without a clear migration story. Layer 19 rehearses how you would detect the regression before it becomes an outage—through JDK-aware CI, structured logs, JFR or async-profiler samples, and tests that assert invariants—not only happy-path compilation. You connect symptoms (Metaspace creep, STW pauses, pool starvation, flaky virtual-thread pinning) back to a language or runtime decision and a fix: clearer APIs, safer concurrency, better defaults, or JVM flags validated with before/after evidence.\n\n**Interview angle:** for layer 19, name one spec-backed guarantee, one metric or dump you would inspect, and one backward-compatible change you would ship first.\n\n### Java 17 records and sealed classes — engineering layer 20\n\nUnder delivery pressure, Java backends accumulate quiet technical debt: raw types slipping past code review, streams that allocate more than expected, locks taken in inconsistent order, or modern syntax used without a clear migration story. Layer 20 rehearses how you would detect the regression before it becomes an outage—through JDK-aware CI, structured logs, JFR or async-profiler samples, and tests that assert invariants—not only happy-path compilation. You connect symptoms (Metaspace creep, STW pauses, pool starvation, flaky virtual-thread pinning) back to a language or runtime decision and a fix: clearer APIs, safer concurrency, better defaults, or JVM flags validated with before/after evidence.\n\n**Interview angle:** for layer 20, name one spec-backed guarantee, one metric or dump you would inspect, and one backward-compatible change you would ship first.\n\n### Java 17 records and sealed classes — engineering layer 21\n\nUnder delivery pressure, Java backends accumulate quiet technical debt: raw types slipping past code review, streams that allocate more than expected, locks taken in inconsistent order, or modern syntax used without a clear migration story. Layer 21 rehearses how you would detect the regression before it becomes an outage—through JDK-aware CI, structured logs, JFR or async-profiler samples, and tests that assert invariants—not only happy-path compilation. You connect symptoms (Metaspace creep, STW pauses, pool starvation, flaky virtual-thread pinning) back to a language or runtime decision and a fix: clearer APIs, safer concurrency, better defaults, or JVM flags validated with before/after evidence.\n\n**Interview angle:** for layer 21, name one spec-backed guarantee, one metric or dump you would inspect, and one backward-compatible change you would ship first.\n\n### Java 17 records and sealed classes — engineering layer 22\n\nUnder delivery pressure, Java backends accumulate quiet technical debt: raw types slipping past code review, streams that allocate more than expected, locks taken in inconsistent order, or modern syntax used without a clear migration story. Layer 22 rehearses how you would detect the regression before it becomes an outage—through JDK-aware CI, structured logs, JFR or async-profiler samples, and tests that assert invariants—not only happy-path compilation. You connect symptoms (Metaspace creep, STW pauses, pool starvation, flaky virtual-thread pinning) back to a language or runtime decision and a fix: clearer APIs, safer concurrency, better defaults, or JVM flags validated with before/after evidence.\n\n**Interview angle:** for layer 22, name one spec-backed guarantee, one metric or dump you would inspect, and one backward-compatible change you would ship first.\n\n### Java 17 records and sealed classes — engineering layer 23\n\nUnder delivery pressure, Java backends accumulate quiet technical debt: raw types slipping past code review, streams that allocate more than expected, locks taken in inconsistent order, or modern syntax used without a clear migration story. Layer 23 rehearses how you would detect the regression before it becomes an outage—through JDK-aware CI, structured logs, JFR or async-profiler samples, and tests that assert invariants—not only happy-path compilation. You connect symptoms (Metaspace creep, STW pauses, pool starvation, flaky virtual-thread pinning) back to a language or runtime decision and a fix: clearer APIs, safer concurrency, better defaults, or JVM flags validated with before/after evidence.\n\n**Interview angle:** for layer 23, name one spec-backed guarantee, one metric or dump you would inspect, and one backward-compatible change you would ship first.\n\n### Java 17 records and sealed classes — engineering layer 24\n\nUnder delivery pressure, Java backends accumulate quiet technical debt: raw types slipping past code review, streams that allocate more than expected, locks taken in inconsistent order, or modern syntax used without a clear migration story. Layer 24 rehearses how you would detect the regression before it becomes an outage—through JDK-aware CI, structured logs, JFR or async-profiler samples, and tests that assert invariants—not only happy-path compilation. You connect symptoms (Metaspace creep, STW pauses, pool starvation, flaky virtual-thread pinning) back to a language or runtime decision and a fix: clearer APIs, safer concurrency, better defaults, or JVM flags validated with before/after evidence.\n\n**Interview angle:** for layer 24, name one spec-backed guarantee, one metric or dump you would inspect, and one backward-compatible change you would ship first.\n\n### Java 17 records and sealed classes — engineering layer 25\n\nUnder delivery pressure, Java backends accumulate quiet technical debt: raw types slipping past code review, streams that allocate more than expected, locks taken in inconsistent order, or modern syntax used without a clear migration story. Layer 25 rehearses how you would detect the regression before it becomes an outage—through JDK-aware CI, structured logs, JFR or async-profiler samples, and tests that assert invariants—not only happy-path compilation. You connect symptoms (Metaspace creep, STW pauses, pool starvation, flaky virtual-thread pinning) back to a language or runtime decision and a fix: clearer APIs, safer concurrency, better defaults, or JVM flags validated with before/after evidence.\n\n**Interview angle:** for layer 25, name one spec-backed guarantee, one metric or dump you would inspect, and one backward-compatible change you would ship first.\n"
    },
    {
      "type": "code",
      "title": "Java 17 Records and Sealed Classes — basic",
      "language": "java",
      "filename": "Day32Basic.java",
      "level": "basic",
      "description": "Deterministic reference: core syntax and one minimal end-to-end print.",
      "code": "package arch.day32;\n\npublic class Day32Basic {\n\n    record Point(int x, int y) {}\n\n    public static void main(String[] args) {\n        Point p = new Point(2, 3);\n        System.out.println(p.x() + p.y());\n        System.out.println(p);\n    }\n}\n",
      "output": "5\nPoint[x=2, y=3]\n"
    },
    {
      "type": "code",
      "title": "Java 17 Records and Sealed Classes — intermediate",
      "language": "java",
      "filename": "Day32Intermediate.java",
      "level": "intermediate",
      "description": "Four labeled scenarios contrasting APIs, safety, and readability.",
      "code": "package arch.day32;\n\npublic class Day32Intermediate {\n\n    public sealed interface Shape permits Circle, Rectangle {\n        double area();\n    }\n\n    public record Circle(double r) implements Shape {\n\n        public Circle {\n            if (r < 0) throw new IllegalArgumentException(\"r\");\n        }\n\n        @Override\n        public double area() {\n            return Math.PI * r * r;\n        }\n    }\n\n    public record Rectangle(double w, double h) implements Shape {\n\n        public Rectangle {\n            if (w < 0 || h < 0) throw new IllegalArgumentException(\"dim\");\n        }\n\n        @Override\n        public double area() {\n            return w * h;\n        }\n    }\n\n    static String label(Shape s) {\n        return switch (s) {\n            case Circle c -> \"circle:\" + (int) c.area();\n            case Rectangle r -> \"rect:\" + (int) r.area();\n        };\n    }\n\n    public static void main(String[] args) {\n        // --- Scenario 1: circle ---\n        System.out.println(\"--- Scenario 1 ---\");\n        System.out.println(label(new Circle(1)));\n        System.out.println();\n\n        // --- Scenario 2: rectangle ---\n        System.out.println(\"--- Scenario 2 ---\");\n        System.out.println(label(new Rectangle(3, 4)));\n        System.out.println();\n\n        // --- Scenario 3: record equals ---\n        System.out.println(\"--- Scenario 3 ---\");\n        System.out.println(new Circle(2).equals(new Circle(2)));\n        System.out.println();\n\n        // --- Scenario 4: compact ctor ---\n        System.out.println(\"--- Scenario 4 ---\");\n        try {\n            new Rectangle(-1, 2);\n            System.out.println(\"bad\");\n        } catch (IllegalArgumentException e) {\n            System.out.println(\"caught\");\n        }\n    }\n}\n",
      "output": "--- Scenario 1 ---\ncircle:3\n\n--- Scenario 2 ---\nrect:12\n\n--- Scenario 3 ---\ntrue\n\n--- Scenario 4 ---\ncaught\n"
    },
    {
      "type": "code",
      "title": "Java 17 Records and Sealed Classes — advanced",
      "language": "java",
      "filename": "Day32Advanced.java",
      "level": "advanced",
      "description": "Three blocks plus printed decision or reference table for tradeoffs.",
      "code": "package arch.day32;\n\npublic class Day32Advanced {\n\n    record Range(int lo, int hi) {\n        Range {\n            if (lo > hi) throw new IllegalArgumentException(\"lo>hi\");\n        }\n    }\n\n    public static void main(String[] args) {\n        // === Block 1: sealed benefit ===\n        System.out.println(\"=== Block 1 ===\");\n        System.out.println(\"Exhaustive switch over sealed hierarchy\");\n        System.out.println();\n\n        // === Block 2: table ===\n        System.out.println(\"=== Block 2 ===\");\n        System.out.println(\"record: data carrier\");\n        System.out.println(\"sealed: closed hierarchy\");\n        System.out.println(\"non-sealed: open extension\");\n        System.out.println();\n\n        // === Block 3: Range ===\n        System.out.println(\"=== Block 3 ===\");\n        Range r = new Range(1, 5);\n        System.out.println(r.lo() + \"-\" + r.hi());\n    }\n}\n",
      "output": "=== Block 1 ===\nExhaustive switch over sealed hierarchy\n\n=== Block 2 ===\nrecord: data carrier\nsealed: closed hierarchy\nnon-sealed: open extension\n\n=== Block 3 ===\n1-5\n"
    },
    {
      "type": "diagram",
      "title": "Sealed hierarchy and exhaustive switch",
      "diagramType": "sequence",
      "description": "Compiler knows permitted subtypes; switch covers all; refactor breaks compile if new subtype missing.",
      "plantuml": "@startuml\ntitle Day 32 — sealed + switch check\n\nparticipant Dev as D\nparticipant \"javac\\nsealed graph\" as C\nparticipant \"Switch\\ncoverage\" as S\nparticipant \"New subtype\" as N\nparticipant Review as R\nparticipant CI as I\n\nD -> C : declare permits A,B\nC -> S : verify patterns\nD -> S : switch cases\nalt missing case when adding C\n  N -> C : add permits C\n  C -> I : compile fails\n  I -> R : fix switch\nelse complete\n  S -> I : green build\nend\n@enduml"
    },
    {
      "type": "pitfalls",
      "title": "Common pitfalls",
      "items": [
        "**Mutable component references** — record looks immutable but internal list mutates; copy defensively.",
        "**Synchronizing on record** — value-based warning; use explicit locks.",
        "**JPA lazy proxies vs records** — mapping mismatch; use entities as classes.",
        "**Sealed permits incomplete** — compile errors; coordinate module boundaries.",
        "**Forgotten switch case** — when not total; enable exhaustive switches.",
        "**Assuming JSON auto polymorphism** — configure type ids for sealed trees.",
        "**Huge record tuples** — unreadable; refactor to nested value types.",
        "**Public API binary compat** — changing components breaks clients; version carefully."
      ]
    },
    {
      "type": "exercise",
      "title": "Practice exercise",
      "difficulty": "Intermediate",
      "problem": "**Day 32 — Records and sealed classes (assignment alignment)**\n\n1. Declare a **sealed interface Shape** with **permits** exactly **Circle** and **Rectangle** (nested or package-private types in the same compilation unit).\n2. Implement **record Circle(double radius)** and **record Rectangle(double width, double height)** implementing **Shape** with **area()** using **Math.PI** for circles.\n3. Add a **total switch expression** (or statement) that returns **area** for each shape type.\n4. In **main**, print **integer cast** areas for **Circle(1)** and **Rectangle(2,3)** on separate lines.",
      "hints": [
        "Use switch (s) { case Circle c -> ... case Rectangle r -> ... } with return type double.",
        "Circle area Math.PI * r * r; Rectangle w*h.",
        "Package arch.day32, class Day32Exercise."
      ],
      "solution": "package arch.day32;\n\npublic class Day32Exercise {\n\n    sealed interface Shape permits Circle, Rectangle {\n        double area();\n    }\n\n    record Circle(double radius) implements Shape {\n\n        @Override\n        public double area() {\n            return Math.PI * radius * radius;\n        }\n    }\n\n    record Rectangle(double width, double height) implements Shape {\n\n        @Override\n        public double area() {\n            return width * height;\n        }\n    }\n\n    static int areaInt(Shape s) {\n        return (int) switch (s) {\n            case Circle c -> c.area();\n            case Rectangle r -> r.area();\n        };\n    }\n\n    public static void main(String[] args) {\n        System.out.println(areaInt(new Circle(1)));\n        System.out.println(areaInt(new Rectangle(2, 3)));\n    }\n}\n"
    },
    {
      "type": "interview",
      "title": "Interview Drill",
      "conceptual": [
        {
          "question": "What is a record?",
          "answer": "Immutable data carrier with generated accessors and equals/hashCode/toString.",
          "followUps": [
            {
              "question": "Interview follow-up: how would you **verify** this in a running service?",
              "answer": "For this topic, you name concrete signals: thread dumps for lock ordering, JFR for allocation hot spots, logs for suppressed warnings, and metrics for pool saturation. You describe a minimal reproducer or integration test that encodes the invariant, and you avoid hand-wavy claims by tying behaviour to JDK version and documented semantics."
            },
            {
              "question": "What **follow-up trap** might the interviewer set?",
              "answer": "They may push on binary compatibility, preview features, migration from older JDKs, or subtle happens-before edges. You respond with scope: what is guaranteed by the JLS or JVM spec versus what is implementation detail, and when to prefer explicit, boring code over clever syntax."
            }
          ]
        },
        {
          "question": "Sealed type purpose?",
          "answer": "Restrict permitted subtypes for safe exhaustive reasoning.",
          "followUps": [
            {
              "question": "Interview follow-up: how would you **verify** this in a running service?",
              "answer": "For this topic, you name concrete signals: thread dumps for lock ordering, JFR for allocation hot spots, logs for suppressed warnings, and metrics for pool saturation. You describe a minimal reproducer or integration test that encodes the invariant, and you avoid hand-wavy claims by tying behaviour to JDK version and documented semantics."
            },
            {
              "question": "What **follow-up trap** might the interviewer set?",
              "answer": "They may push on binary compatibility, preview features, migration from older JDKs, or subtle happens-before edges. You respond with scope: what is guaranteed by the JLS or JVM spec versus what is implementation detail, and when to prefer explicit, boring code over clever syntax."
            }
          ]
        },
        {
          "question": "Compact constructor?",
          "answer": "Validates/normalizes before implicit field assignment.",
          "followUps": [
            {
              "question": "Interview follow-up: how would you **verify** this in a running service?",
              "answer": "For this topic, you name concrete signals: thread dumps for lock ordering, JFR for allocation hot spots, logs for suppressed warnings, and metrics for pool saturation. You describe a minimal reproducer or integration test that encodes the invariant, and you avoid hand-wavy claims by tying behaviour to JDK version and documented semantics."
            },
            {
              "question": "What **follow-up trap** might the interviewer set?",
              "answer": "They may push on binary compatibility, preview features, migration from older JDKs, or subtle happens-before edges. You respond with scope: what is guaranteed by the JLS or JVM spec versus what is implementation detail, and when to prefer explicit, boring code over clever syntax."
            }
          ]
        },
        {
          "question": "Why exhaustive switch matters?",
          "answer": "Compiler forces updates when hierarchy grows.",
          "followUps": [
            {
              "question": "Interview follow-up: how would you **verify** this in a running service?",
              "answer": "For this topic, you name concrete signals: thread dumps for lock ordering, JFR for allocation hot spots, logs for suppressed warnings, and metrics for pool saturation. You describe a minimal reproducer or integration test that encodes the invariant, and you avoid hand-wavy claims by tying behaviour to JDK version and documented semantics."
            },
            {
              "question": "What **follow-up trap** might the interviewer set?",
              "answer": "They may push on binary compatibility, preview features, migration from older JDKs, or subtle happens-before edges. You respond with scope: what is guaranteed by the JLS or JVM spec versus what is implementation detail, and when to prefer explicit, boring code over clever syntax."
            }
          ]
        },
        {
          "question": "Record vs Lombok?",
          "answer": "Language feature; clearer semantics and reflection.",
          "followUps": [
            {
              "question": "Interview follow-up: how would you **verify** this in a running service?",
              "answer": "For this topic, you name concrete signals: thread dumps for lock ordering, JFR for allocation hot spots, logs for suppressed warnings, and metrics for pool saturation. You describe a minimal reproducer or integration test that encodes the invariant, and you avoid hand-wavy claims by tying behaviour to JDK version and documented semantics."
            },
            {
              "question": "What **follow-up trap** might the interviewer set?",
              "answer": "They may push on binary compatibility, preview features, migration from older JDKs, or subtle happens-before edges. You respond with scope: what is guaranteed by the JLS or JVM spec versus what is implementation detail, and when to prefer explicit, boring code over clever syntax."
            }
          ]
        },
        {
          "question": "non-sealed meaning?",
          "answer": "Subtype opens hierarchy again.",
          "followUps": [
            {
              "question": "Interview follow-up: how would you **verify** this in a running service?",
              "answer": "For this topic, you name concrete signals: thread dumps for lock ordering, JFR for allocation hot spots, logs for suppressed warnings, and metrics for pool saturation. You describe a minimal reproducer or integration test that encodes the invariant, and you avoid hand-wavy claims by tying behaviour to JDK version and documented semantics."
            },
            {
              "question": "What **follow-up trap** might the interviewer set?",
              "answer": "They may push on binary compatibility, preview features, migration from older JDKs, or subtle happens-before edges. You respond with scope: what is guaranteed by the JLS or JVM spec versus what is implementation detail, and when to prefer explicit, boring code over clever syntax."
            }
          ]
        },
        {
          "question": "Can record extend class?",
          "answer": "No; extends Record implicitly.",
          "followUps": [
            {
              "question": "Interview follow-up: how would you **verify** this in a running service?",
              "answer": "For this topic, you name concrete signals: thread dumps for lock ordering, JFR for allocation hot spots, logs for suppressed warnings, and metrics for pool saturation. You describe a minimal reproducer or integration test that encodes the invariant, and you avoid hand-wavy claims by tying behaviour to JDK version and documented semantics."
            },
            {
              "question": "What **follow-up trap** might the interviewer set?",
              "answer": "They may push on binary compatibility, preview features, migration from older JDKs, or subtle happens-before edges. You respond with scope: what is guaranteed by the JLS or JVM spec versus what is implementation detail, and when to prefer explicit, boring code over clever syntax."
            }
          ]
        },
        {
          "question": "JPA with records?",
          "answer": "DTOs yes; mutable entities usually classes.",
          "followUps": [
            {
              "question": "Interview follow-up: how would you **verify** this in a running service?",
              "answer": "For this topic, you name concrete signals: thread dumps for lock ordering, JFR for allocation hot spots, logs for suppressed warnings, and metrics for pool saturation. You describe a minimal reproducer or integration test that encodes the invariant, and you avoid hand-wavy claims by tying behaviour to JDK version and documented semantics."
            },
            {
              "question": "What **follow-up trap** might the interviewer set?",
              "answer": "They may push on binary compatibility, preview features, migration from older JDKs, or subtle happens-before edges. You respond with scope: what is guaranteed by the JLS or JVM spec versus what is implementation detail, and when to prefer explicit, boring code over clever syntax."
            }
          ]
        },
        {
          "question": "Serialization concerns?",
          "answer": "Compatibility and evolution of components.",
          "followUps": [
            {
              "question": "Interview follow-up: how would you **verify** this in a running service?",
              "answer": "For this topic, you name concrete signals: thread dumps for lock ordering, JFR for allocation hot spots, logs for suppressed warnings, and metrics for pool saturation. You describe a minimal reproducer or integration test that encodes the invariant, and you avoid hand-wavy claims by tying behaviour to JDK version and documented semantics."
            },
            {
              "question": "What **follow-up trap** might the interviewer set?",
              "answer": "They may push on binary compatibility, preview features, migration from older JDKs, or subtle happens-before edges. You respond with scope: what is guaranteed by the JLS or JVM spec versus what is implementation detail, and when to prefer explicit, boring code over clever syntax."
            }
          ]
        },
        {
          "question": "Accessor naming?",
          "answer": "name() not getName by default.",
          "followUps": [
            {
              "question": "Interview follow-up: how would you **verify** this in a running service?",
              "answer": "For this topic, you name concrete signals: thread dumps for lock ordering, JFR for allocation hot spots, logs for suppressed warnings, and metrics for pool saturation. You describe a minimal reproducer or integration test that encodes the invariant, and you avoid hand-wavy claims by tying behaviour to JDK version and documented semantics."
            },
            {
              "question": "What **follow-up trap** might the interviewer set?",
              "answer": "They may push on binary compatibility, preview features, migration from older JDKs, or subtle happens-before edges. You respond with scope: what is guaranteed by the JLS or JVM spec versus what is implementation detail, and when to prefer explicit, boring code over clever syntax."
            }
          ]
        },
        {
          "question": "Permits across modules?",
          "answer": "Module readability constraints.",
          "followUps": [
            {
              "question": "Interview follow-up: how would you **verify** this in a running service?",
              "answer": "For this topic, you name concrete signals: thread dumps for lock ordering, JFR for allocation hot spots, logs for suppressed warnings, and metrics for pool saturation. You describe a minimal reproducer or integration test that encodes the invariant, and you avoid hand-wavy claims by tying behaviour to JDK version and documented semantics."
            },
            {
              "question": "What **follow-up trap** might the interviewer set?",
              "answer": "They may push on binary compatibility, preview features, migration from older JDKs, or subtle happens-before edges. You respond with scope: what is guaranteed by the JLS or JVM spec versus what is implementation detail, and when to prefer explicit, boring code over clever syntax."
            }
          ]
        },
        {
          "question": "Value-based warnings?",
          "answer": "Do not synchronize on records.",
          "followUps": [
            {
              "question": "Interview follow-up: how would you **verify** this in a running service?",
              "answer": "For this topic, you name concrete signals: thread dumps for lock ordering, JFR for allocation hot spots, logs for suppressed warnings, and metrics for pool saturation. You describe a minimal reproducer or integration test that encodes the invariant, and you avoid hand-wavy claims by tying behaviour to JDK version and documented semantics."
            },
            {
              "question": "What **follow-up trap** might the interviewer set?",
              "answer": "They may push on binary compatibility, preview features, migration from older JDKs, or subtle happens-before edges. You respond with scope: what is guaranteed by the JLS or JVM spec versus what is implementation detail, and when to prefer explicit, boring code over clever syntax."
            }
          ]
        },
        {
          "question": "Pattern matching synergy?",
          "answer": "Sealed + records simplify switches.",
          "followUps": [
            {
              "question": "Interview follow-up: how would you **verify** this in a running service?",
              "answer": "For this topic, you name concrete signals: thread dumps for lock ordering, JFR for allocation hot spots, logs for suppressed warnings, and metrics for pool saturation. You describe a minimal reproducer or integration test that encodes the invariant, and you avoid hand-wavy claims by tying behaviour to JDK version and documented semantics."
            },
            {
              "question": "What **follow-up trap** might the interviewer set?",
              "answer": "They may push on binary compatibility, preview features, migration from older JDKs, or subtle happens-before edges. You respond with scope: what is guaranteed by the JLS or JVM spec versus what is implementation detail, and when to prefer explicit, boring code over clever syntax."
            }
          ]
        },
        {
          "question": "Domain modeling example?",
          "answer": "Payment events as sealed interface variants.",
          "followUps": [
            {
              "question": "Interview follow-up: how would you **verify** this in a running service?",
              "answer": "For this topic, you name concrete signals: thread dumps for lock ordering, JFR for allocation hot spots, logs for suppressed warnings, and metrics for pool saturation. You describe a minimal reproducer or integration test that encodes the invariant, and you avoid hand-wavy claims by tying behaviour to JDK version and documented semantics."
            },
            {
              "question": "What **follow-up trap** might the interviewer set?",
              "answer": "They may push on binary compatibility, preview features, migration from older JDKs, or subtle happens-before edges. You respond with scope: what is guaranteed by the JLS or JVM spec versus what is implementation detail, and when to prefer explicit, boring code over clever syntax."
            }
          ]
        },
        {
          "question": "Immutability caveat?",
          "answer": "If component is mutable object, record still mutable inside.",
          "followUps": [
            {
              "question": "Interview follow-up: how would you **verify** this in a running service?",
              "answer": "For this topic, you name concrete signals: thread dumps for lock ordering, JFR for allocation hot spots, logs for suppressed warnings, and metrics for pool saturation. You describe a minimal reproducer or integration test that encodes the invariant, and you avoid hand-wavy claims by tying behaviour to JDK version and documented semantics."
            },
            {
              "question": "What **follow-up trap** might the interviewer set?",
              "answer": "They may push on binary compatibility, preview features, migration from older JDKs, or subtle happens-before edges. You respond with scope: what is guaranteed by the JLS or JVM spec versus what is implementation detail, and when to prefer explicit, boring code over clever syntax."
            }
          ]
        },
        {
          "question": "Reflection components?",
          "answer": "RecordComponent metadata.",
          "followUps": [
            {
              "question": "Interview follow-up: how would you **verify** this in a running service?",
              "answer": "For this topic, you name concrete signals: thread dumps for lock ordering, JFR for allocation hot spots, logs for suppressed warnings, and metrics for pool saturation. You describe a minimal reproducer or integration test that encodes the invariant, and you avoid hand-wavy claims by tying behaviour to JDK version and documented semantics."
            },
            {
              "question": "What **follow-up trap** might the interviewer set?",
              "answer": "They may push on binary compatibility, preview features, migration from older JDKs, or subtle happens-before edges. You respond with scope: what is guaranteed by the JLS or JVM spec versus what is implementation detail, and when to prefer explicit, boring code over clever syntax."
            }
          ]
        },
        {
          "question": "60-second record story?",
          "answer": "DTO, validation, sealed, exhaustive switch, no setters.",
          "followUps": [
            {
              "question": "Interview follow-up: how would you **verify** this in a running service?",
              "answer": "For this topic, you name concrete signals: thread dumps for lock ordering, JFR for allocation hot spots, logs for suppressed warnings, and metrics for pool saturation. You describe a minimal reproducer or integration test that encodes the invariant, and you avoid hand-wavy claims by tying behaviour to JDK version and documented semantics."
            },
            {
              "question": "What **follow-up trap** might the interviewer set?",
              "answer": "They may push on binary compatibility, preview features, migration from older JDKs, or subtle happens-before edges. You respond with scope: what is guaranteed by the JLS or JVM spec versus what is implementation detail, and when to prefer explicit, boring code over clever syntax."
            }
          ]
        }
      ],
      "codeBased": [
        {
          "question": "Area switch sealed Shape?",
          "answer": "switch (s) { case Circle c -> ... case Rect r -> ... }.",
          "followUps": [
            {
              "question": "Interview follow-up: how would you **verify** this in a running service?",
              "answer": "For this code path, you name concrete signals: thread dumps for lock ordering, JFR for allocation hot spots, logs for suppressed warnings, and metrics for pool saturation. You describe a minimal reproducer or integration test that encodes the invariant, and you avoid hand-wavy claims by tying behaviour to JDK version and documented semantics."
            },
            {
              "question": "What **follow-up trap** might the interviewer set?",
              "answer": "They may push on binary compatibility, preview features, migration from older JDKs, or subtle happens-before edges. You respond with scope: what is guaranteed by the JLS or JVM spec versus what is implementation detail, and when to prefer explicit, boring code over clever syntax."
            }
          ]
        },
        {
          "question": "Validate record input?",
          "answer": "Compact constructor throws on invalid.",
          "followUps": [
            {
              "question": "Interview follow-up: how would you **verify** this in a running service?",
              "answer": "For this code path, you name concrete signals: thread dumps for lock ordering, JFR for allocation hot spots, logs for suppressed warnings, and metrics for pool saturation. You describe a minimal reproducer or integration test that encodes the invariant, and you avoid hand-wavy claims by tying behaviour to JDK version and documented semantics."
            },
            {
              "question": "What **follow-up trap** might the interviewer set?",
              "answer": "They may push on binary compatibility, preview features, migration from older JDKs, or subtle happens-before edges. You respond with scope: what is guaranteed by the JLS or JVM spec versus what is implementation detail, and when to prefer explicit, boring code over clever syntax."
            }
          ]
        },
        {
          "question": "equals two records?",
          "answer": "Component-wise by default.",
          "followUps": [
            {
              "question": "Interview follow-up: how would you **verify** this in a running service?",
              "answer": "For this code path, you name concrete signals: thread dumps for lock ordering, JFR for allocation hot spots, logs for suppressed warnings, and metrics for pool saturation. You describe a minimal reproducer or integration test that encodes the invariant, and you avoid hand-wavy claims by tying behaviour to JDK version and documented semantics."
            },
            {
              "question": "What **follow-up trap** might the interviewer set?",
              "answer": "They may push on binary compatibility, preview features, migration from older JDKs, or subtle happens-before edges. You respond with scope: what is guaranteed by the JLS or JVM spec versus what is implementation detail, and when to prefer explicit, boring code over clever syntax."
            }
          ]
        },
        {
          "question": "Implement interface in record?",
          "answer": "record R(...) implements I { }.",
          "followUps": [
            {
              "question": "Interview follow-up: how would you **verify** this in a running service?",
              "answer": "For this code path, you name concrete signals: thread dumps for lock ordering, JFR for allocation hot spots, logs for suppressed warnings, and metrics for pool saturation. You describe a minimal reproducer or integration test that encodes the invariant, and you avoid hand-wavy claims by tying behaviour to JDK version and documented semantics."
            },
            {
              "question": "What **follow-up trap** might the interviewer set?",
              "answer": "They may push on binary compatibility, preview features, migration from older JDKs, or subtle happens-before edges. You respond with scope: what is guaranteed by the JLS or JVM spec versus what is implementation detail, and when to prefer explicit, boring code over clever syntax."
            }
          ]
        },
        {
          "question": "Add method to record?",
          "answer": "Instance methods allowed.",
          "followUps": [
            {
              "question": "Interview follow-up: how would you **verify** this in a running service?",
              "answer": "For this code path, you name concrete signals: thread dumps for lock ordering, JFR for allocation hot spots, logs for suppressed warnings, and metrics for pool saturation. You describe a minimal reproducer or integration test that encodes the invariant, and you avoid hand-wavy claims by tying behaviour to JDK version and documented semantics."
            },
            {
              "question": "What **follow-up trap** might the interviewer set?",
              "answer": "They may push on binary compatibility, preview features, migration from older JDKs, or subtle happens-before edges. You respond with scope: what is guaranteed by the JLS or JVM spec versus what is implementation detail, and when to prefer explicit, boring code over clever syntax."
            }
          ]
        },
        {
          "question": "Static field in record?",
          "answer": "Allowed.",
          "followUps": [
            {
              "question": "Interview follow-up: how would you **verify** this in a running service?",
              "answer": "For this code path, you name concrete signals: thread dumps for lock ordering, JFR for allocation hot spots, logs for suppressed warnings, and metrics for pool saturation. You describe a minimal reproducer or integration test that encodes the invariant, and you avoid hand-wavy claims by tying behaviour to JDK version and documented semantics."
            },
            {
              "question": "What **follow-up trap** might the interviewer set?",
              "answer": "They may push on binary compatibility, preview features, migration from older JDKs, or subtle happens-before edges. You respond with scope: what is guaranteed by the JLS or JVM spec versus what is implementation detail, and when to prefer explicit, boring code over clever syntax."
            }
          ]
        },
        {
          "question": "Generic record?",
          "answer": "record Pair<T>(T a, T b).",
          "followUps": [
            {
              "question": "Interview follow-up: how would you **verify** this in a running service?",
              "answer": "For this code path, you name concrete signals: thread dumps for lock ordering, JFR for allocation hot spots, logs for suppressed warnings, and metrics for pool saturation. You describe a minimal reproducer or integration test that encodes the invariant, and you avoid hand-wavy claims by tying behaviour to JDK version and documented semantics."
            },
            {
              "question": "What **follow-up trap** might the interviewer set?",
              "answer": "They may push on binary compatibility, preview features, migration from older JDKs, or subtle happens-before edges. You respond with scope: what is guaranteed by the JLS or JVM spec versus what is implementation detail, and when to prefer explicit, boring code over clever syntax."
            }
          ]
        },
        {
          "question": "Sealed permits in nested?",
          "answer": "Inner types permitted list.",
          "followUps": [
            {
              "question": "Interview follow-up: how would you **verify** this in a running service?",
              "answer": "For this code path, you name concrete signals: thread dumps for lock ordering, JFR for allocation hot spots, logs for suppressed warnings, and metrics for pool saturation. You describe a minimal reproducer or integration test that encodes the invariant, and you avoid hand-wavy claims by tying behaviour to JDK version and documented semantics."
            },
            {
              "question": "What **follow-up trap** might the interviewer set?",
              "answer": "They may push on binary compatibility, preview features, migration from older JDKs, or subtle happens-before edges. You respond with scope: what is guaranteed by the JLS or JVM spec versus what is implementation detail, and when to prefer explicit, boring code over clever syntax."
            }
          ]
        },
        {
          "question": "Switch expression yield?",
          "answer": "Use arrow or yield in blocks.",
          "followUps": [
            {
              "question": "Interview follow-up: how would you **verify** this in a running service?",
              "answer": "For this code path, you name concrete signals: thread dumps for lock ordering, JFR for allocation hot spots, logs for suppressed warnings, and metrics for pool saturation. You describe a minimal reproducer or integration test that encodes the invariant, and you avoid hand-wavy claims by tying behaviour to JDK version and documented semantics."
            },
            {
              "question": "What **follow-up trap** might the interviewer set?",
              "answer": "They may push on binary compatibility, preview features, migration from older JDKs, or subtle happens-before edges. You respond with scope: what is guaranteed by the JLS or JVM spec versus what is implementation detail, and when to prefer explicit, boring code over clever syntax."
            }
          ]
        },
        {
          "question": "Record serialization?",
          "answer": "Same mechanisms as class; design serial form.",
          "followUps": [
            {
              "question": "Interview follow-up: how would you **verify** this in a running service?",
              "answer": "For this code path, you name concrete signals: thread dumps for lock ordering, JFR for allocation hot spots, logs for suppressed warnings, and metrics for pool saturation. You describe a minimal reproducer or integration test that encodes the invariant, and you avoid hand-wavy claims by tying behaviour to JDK version and documented semantics."
            },
            {
              "question": "What **follow-up trap** might the interviewer set?",
              "answer": "They may push on binary compatibility, preview features, migration from older JDKs, or subtle happens-before edges. You respond with scope: what is guaranteed by the JLS or JVM spec versus what is implementation detail, and when to prefer explicit, boring code over clever syntax."
            }
          ]
        },
        {
          "question": "Copy with change?",
          "answer": "with pattern manual or new record.",
          "followUps": [
            {
              "question": "Interview follow-up: how would you **verify** this in a running service?",
              "answer": "For this code path, you name concrete signals: thread dumps for lock ordering, JFR for allocation hot spots, logs for suppressed warnings, and metrics for pool saturation. You describe a minimal reproducer or integration test that encodes the invariant, and you avoid hand-wavy claims by tying behaviour to JDK version and documented semantics."
            },
            {
              "question": "What **follow-up trap** might the interviewer set?",
              "answer": "They may push on binary compatibility, preview features, migration from older JDKs, or subtle happens-before edges. You respond with scope: what is guaranteed by the JLS or JVM spec versus what is implementation detail, and when to prefer explicit, boring code over clever syntax."
            }
          ]
        },
        {
          "question": "Avoid record for service?",
          "answer": "Stateful beans not ideal as records.",
          "followUps": [
            {
              "question": "Interview follow-up: how would you **verify** this in a running service?",
              "answer": "For this code path, you name concrete signals: thread dumps for lock ordering, JFR for allocation hot spots, logs for suppressed warnings, and metrics for pool saturation. You describe a minimal reproducer or integration test that encodes the invariant, and you avoid hand-wavy claims by tying behaviour to JDK version and documented semantics."
            },
            {
              "question": "What **follow-up trap** might the interviewer set?",
              "answer": "They may push on binary compatibility, preview features, migration from older JDKs, or subtle happens-before edges. You respond with scope: what is guaranteed by the JLS or JVM spec versus what is implementation detail, and when to prefer explicit, boring code over clever syntax."
            }
          ]
        }
      ],
      "seniorScenario": [
        {
          "question": "API evolution add subtype?",
          "answer": "Update permits + all switches; communicate clients.",
          "followUps": [
            {
              "question": "Interview follow-up: how would you **verify** this in a running service?",
              "answer": "For this scenario, you name concrete signals: thread dumps for lock ordering, JFR for allocation hot spots, logs for suppressed warnings, and metrics for pool saturation. You describe a minimal reproducer or integration test that encodes the invariant, and you avoid hand-wavy claims by tying behaviour to JDK version and documented semantics."
            },
            {
              "question": "What **follow-up trap** might the interviewer set?",
              "answer": "They may push on binary compatibility, preview features, migration from older JDKs, or subtle happens-before edges. You respond with scope: what is guaranteed by the JLS or JVM spec versus what is implementation detail, and when to prefer explicit, boring code over clever syntax."
            }
          ]
        },
        {
          "question": "JSON polymorphic sealed?",
          "answer": "Type discriminator config in mapper.",
          "followUps": [
            {
              "question": "Interview follow-up: how would you **verify** this in a running service?",
              "answer": "For this scenario, you name concrete signals: thread dumps for lock ordering, JFR for allocation hot spots, logs for suppressed warnings, and metrics for pool saturation. You describe a minimal reproducer or integration test that encodes the invariant, and you avoid hand-wavy claims by tying behaviour to JDK version and documented semantics."
            },
            {
              "question": "What **follow-up trap** might the interviewer set?",
              "answer": "They may push on binary compatibility, preview features, migration from older JDKs, or subtle happens-before edges. You respond with scope: what is guaranteed by the JLS or JVM spec versus what is implementation detail, and when to prefer explicit, boring code over clever syntax."
            }
          ]
        },
        {
          "question": "Team Lombok migration?",
          "answer": "Gradual; prefer records for new DTOs.",
          "followUps": [
            {
              "question": "Interview follow-up: how would you **verify** this in a running service?",
              "answer": "For this scenario, you name concrete signals: thread dumps for lock ordering, JFR for allocation hot spots, logs for suppressed warnings, and metrics for pool saturation. You describe a minimal reproducer or integration test that encodes the invariant, and you avoid hand-wavy claims by tying behaviour to JDK version and documented semantics."
            },
            {
              "question": "What **follow-up trap** might the interviewer set?",
              "answer": "They may push on binary compatibility, preview features, migration from older JDKs, or subtle happens-before edges. You respond with scope: what is guaranteed by the JLS or JVM spec versus what is implementation detail, and when to prefer explicit, boring code over clever syntax."
            }
          ]
        },
        {
          "question": "Performance record?",
          "answer": "Similar to class; allocation normal.",
          "followUps": [
            {
              "question": "Interview follow-up: how would you **verify** this in a running service?",
              "answer": "For this scenario, you name concrete signals: thread dumps for lock ordering, JFR for allocation hot spots, logs for suppressed warnings, and metrics for pool saturation. You describe a minimal reproducer or integration test that encodes the invariant, and you avoid hand-wavy claims by tying behaviour to JDK version and documented semantics."
            },
            {
              "question": "What **follow-up trap** might the interviewer set?",
              "answer": "They may push on binary compatibility, preview features, migration from older JDKs, or subtle happens-before edges. You respond with scope: what is guaranteed by the JLS or JVM spec versus what is implementation detail, and when to prefer explicit, boring code over clever syntax."
            }
          ]
        },
        {
          "question": "Security sealed?",
          "answer": "Limit implementations for sensitive parsers.",
          "followUps": [
            {
              "question": "Interview follow-up: how would you **verify** this in a running service?",
              "answer": "For this scenario, you name concrete signals: thread dumps for lock ordering, JFR for allocation hot spots, logs for suppressed warnings, and metrics for pool saturation. You describe a minimal reproducer or integration test that encodes the invariant, and you avoid hand-wavy claims by tying behaviour to JDK version and documented semantics."
            },
            {
              "question": "What **follow-up trap** might the interviewer set?",
              "answer": "They may push on binary compatibility, preview features, migration from older JDKs, or subtle happens-before edges. You respond with scope: what is guaranteed by the JLS or JVM spec versus what is implementation detail, and when to prefer explicit, boring code over clever syntax."
            }
          ]
        },
        {
          "question": "Code review sealed?",
          "answer": "Ensure permits minimal; document extension policy.",
          "followUps": [
            {
              "question": "Interview follow-up: how would you **verify** this in a running service?",
              "answer": "For this scenario, you name concrete signals: thread dumps for lock ordering, JFR for allocation hot spots, logs for suppressed warnings, and metrics for pool saturation. You describe a minimal reproducer or integration test that encodes the invariant, and you avoid hand-wavy claims by tying behaviour to JDK version and documented semantics."
            },
            {
              "question": "What **follow-up trap** might the interviewer set?",
              "answer": "They may push on binary compatibility, preview features, migration from older JDKs, or subtle happens-before edges. You respond with scope: what is guaranteed by the JLS or JVM spec versus what is implementation detail, and when to prefer explicit, boring code over clever syntax."
            }
          ]
        }
      ],
      "wrongAnswers": [
        "Records have generated setters — false.",
        "Sealed allows any subclass — false permits list.",
        "Record may extend another class — false.",
        "Exhaustive switch never compile-checked — false for sealed total.",
        "Record equals is identity — false components.",
        "Sealed only for classes — false interfaces too.",
        "Compact ctor runs after fields assigned — false validates before.",
        "Records cannot implement interfaces — false."
      ]
    },
    {
      "type": "mcq",
      "title": "MCQ Quiz — Records and Sealed Classes",
      "description": "Thirty questions on records, sealed types, permits, and exhaustive switches.",
      "questions": [
        {
          "id": 1,
          "level": "basic",
          "category": "theory",
          "question": "Record accessor name:",
          "options": {
            "A": "x() for component x",
            "B": "getX()",
            "C": "x.get",
            "D": "field x public"
          },
          "answer": "A",
          "explanation": "Canonical."
        },
        {
          "id": 2,
          "level": "basic",
          "category": "code",
          "question": "Record equals uses:",
          "options": {
            "A": "Components",
            "B": "Identity only",
            "C": "Random",
            "D": "hashCode 0"
          },
          "answer": "A",
          "explanation": "Value semantics."
        },
        {
          "id": 3,
          "level": "basic",
          "category": "theory",
          "question": "Sealed restricts:",
          "options": {
            "A": "Permitted subclasses",
            "B": "All classes",
            "C": "Interfaces only",
            "D": "Primitives"
          },
          "answer": "A",
          "explanation": "Closed world."
        },
        {
          "id": 4,
          "level": "intermediate",
          "category": "code",
          "question": "Compact constructor:",
          "options": {
            "A": "Validates before assignment",
            "B": "Runs after fields set",
            "C": "Illegal",
            "D": "Only static"
          },
          "answer": "A",
          "explanation": "Record syntax."
        },
        {
          "id": 5,
          "level": "intermediate",
          "category": "theory",
          "question": "Permitted class must be:",
          "options": {
            "A": "final sealed or non-sealed",
            "B": "always abstract",
            "C": "interface",
            "D": "enum"
          },
          "answer": "A",
          "explanation": "JLS rules."
        },
        {
          "id": 6,
          "level": "intermediate",
          "category": "code",
          "question": "Exhaustive switch on sealed:",
          "options": {
            "A": "All permitted types covered",
            "B": "Optional",
            "C": "Runtime only",
            "D": "Never checked"
          },
          "answer": "A",
          "explanation": "Compile-time."
        },
        {
          "id": 7,
          "level": "advanced",
          "category": "theory",
          "question": "Record cannot extend class because:",
          "options": {
            "A": "Implicitly extends Record",
            "B": "sealed forbids",
            "C": "final illegal",
            "D": "no super"
          },
          "answer": "A",
          "explanation": "Inheritance single."
        },
        {
          "id": 8,
          "level": "intermediate",
          "category": "code",
          "question": "Record implements interfaces:",
          "options": {
            "A": "Allowed",
            "B": "Forbidden",
            "C": "Only Serializable",
            "D": "Only one"
          },
          "answer": "A",
          "explanation": "Multiple ok."
        },
        {
          "id": 9,
          "level": "basic",
          "category": "theory",
          "question": "Record is implicitly:",
          "options": {
            "A": "final",
            "B": "abstract",
            "C": "open subclassing",
            "D": "annotation"
          },
          "answer": "A",
          "explanation": "Cannot extend record."
        },
        {
          "id": 10,
          "level": "intermediate",
          "category": "code",
          "question": "non-sealed permits:",
          "options": {
            "A": "Open arbitrary subclasses",
            "B": "No subclasses",
            "C": "Only records",
            "D": "Error"
          },
          "answer": "A",
          "explanation": "Escape hatch."
        },
        {
          "id": 11,
          "level": "intermediate",
          "category": "theory",
          "question": "Record serialization:",
          "options": {
            "A": "Component-wise cautiously",
            "B": "Always unsafe",
            "C": "Banned",
            "D": "Automatic beans"
          },
          "answer": "A",
          "explanation": "Design."
        },
        {
          "id": 12,
          "level": "advanced",
          "category": "code",
          "question": "Reflection getRecordComponents:",
          "options": {
            "A": "Inspect components",
            "B": "Delete fields",
            "C": "Change values",
            "D": "JIT hint"
          },
          "answer": "A",
          "explanation": "Meta."
        },
        {
          "id": 13,
          "level": "intermediate",
          "category": "theory",
          "question": "Sealed in modules:",
          "options": {
            "A": "Same module/package rules apply",
            "B": "Ignored",
            "C": "Only JDK",
            "D": "Android only"
          },
          "answer": "A",
          "explanation": "Encapsulation."
        },
        {
          "id": 14,
          "level": "basic",
          "category": "code",
          "question": "toString generated:",
          "options": {
            "A": "Includes components",
            "B": "Empty",
            "C": "Identity",
            "D": "Random"
          },
          "answer": "A",
          "explanation": "Record."
        },
        {
          "id": 15,
          "level": "intermediate",
          "category": "code",
          "question": "Custom accessor in record:",
          "options": {
            "A": "Can override generated",
            "B": "Impossible",
            "C": "Only static",
            "D": "Two components max"
          },
          "answer": "A",
          "explanation": "Rare."
        },
        {
          "id": 16,
          "level": "advanced",
          "category": "theory",
          "question": "Algebraic data type analogy:",
          "options": {
            "A": "Sealed sum + records product",
            "B": "Only OOP",
            "C": "SQL",
            "D": "GC"
          },
          "answer": "A",
          "explanation": "Modeling."
        },
        {
          "id": 17,
          "level": "intermediate",
          "category": "code",
          "question": "Switch on record patterns:",
          "options": {
            "A": "Deconstruct components",
            "B": "Illegal",
            "C": "Only int",
            "D": "Runtime cast"
          },
          "answer": "A",
          "explanation": "Pattern matching."
        },
        {
          "id": 18,
          "level": "basic",
          "category": "theory",
          "question": "Record vs class boilerplate:",
          "options": {
            "A": "Less for data carriers",
            "B": "More",
            "C": "Same always",
            "D": "No equals"
          },
          "answer": "A",
          "explanation": "DX."
        },
        {
          "id": 19,
          "level": "intermediate",
          "category": "code",
          "question": "Illegal record component name:",
          "options": {
            "A": "Must not clash badly with methods",
            "B": "Any keyword ok",
            "C": "Unicode banned",
            "D": "50 max"
          },
          "answer": "A",
          "explanation": "Rules."
        },
        {
          "id": 20,
          "level": "advanced",
          "category": "theory",
          "question": "JPA entity as record:",
          "options": {
            "A": "Often discouraged; DTO better",
            "B": "Required",
            "C": "Only EJB",
            "D": "Impossible"
          },
          "answer": "A",
          "explanation": "Persistence."
        },
        {
          "id": 21,
          "level": "intermediate",
          "category": "code",
          "question": "Sealed interface permits records:",
          "options": {
            "A": "Yes",
            "B": "No",
            "C": "Only classes",
            "D": "Only enums"
          },
          "answer": "A",
          "explanation": "Modern Java."
        },
        {
          "id": 22,
          "level": "intermediate",
          "category": "theory",
          "question": "Record canonical ctor:",
          "options": {
            "A": "Matches components order",
            "B": "Random order",
            "C": "No args only",
            "D": "private only"
          },
          "answer": "A",
          "explanation": "Language."
        },
        {
          "id": 23,
          "level": "basic",
          "category": "code",
          "question": "hashCode from components:",
          "options": {
            "A": "Generated consistent with equals",
            "B": "Identity",
            "C": "Zero",
            "D": "Random"
          },
          "answer": "A",
          "explanation": "Contract."
        },
        {
          "id": 24,
          "level": "advanced",
          "category": "code",
          "question": "Switch total on sealed exhaustive:",
          "options": {
            "A": "May omit default",
            "B": "Always needs default",
            "C": "Illegal switch",
            "D": "Only int"
          },
          "answer": "A",
          "explanation": "Coverage."
        },
        {
          "id": 25,
          "level": "intermediate",
          "category": "theory",
          "question": "Record mutability:",
          "options": {
            "A": "Components final",
            "B": "All mutable",
            "C": "Only static mutable",
            "D": "volatile components"
          },
          "answer": "A",
          "explanation": "Immutable."
        },
        {
          "id": 26,
          "level": "intermediate",
          "category": "code",
          "question": "Nested record:",
          "options": {
            "A": "Static implicitly",
            "B": "Must be inner non-static",
            "C": "Illegal",
            "D": "Only top-level"
          },
          "answer": "A",
          "explanation": "Nested rules."
        },
        {
          "id": 27,
          "level": "basic",
          "category": "theory",
          "question": "Sealed keyword since:",
          "options": {
            "A": "Java 17",
            "B": "Java 8",
            "C": "Java 1.0",
            "D": "Java 5"
          },
          "answer": "A",
          "explanation": "LTS feature."
        },
        {
          "id": 28,
          "level": "advanced",
          "category": "code",
          "question": "Pattern record case Circle(double r):",
          "options": {
            "A": "Deconstruction pattern",
            "B": "Illegal",
            "C": "Only instanceof",
            "D": "Regex"
          },
          "answer": "A",
          "explanation": "Preview/stable versions."
        },
        {
          "id": 29,
          "level": "intermediate",
          "category": "theory",
          "question": "DTO fit for record:",
          "options": {
            "A": "Strong",
            "B": "Never",
            "C": "Only GUI",
            "D": "Only XML"
          },
          "answer": "A",
          "explanation": "Use case."
        },
        {
          "id": 30,
          "level": "intermediate",
          "category": "code",
          "question": "implements sealed as permitted:",
          "options": {
            "A": "Must be listed in permits",
            "B": "Automatic",
            "C": "Forbidden",
            "D": "Runtime"
          },
          "answer": "A",
          "explanation": "Compile check."
        }
      ]
    },
    {
      "type": "cheatsheet",
      "title": "Java 17 Records and Sealed Classes — cheatsheet",
      "content": "| Topic | Rule of thumb | Interview one-liner |\n| --- | --- | --- |\n| record | immutable carrier | no setters |\n| compact ctor | validate | before fields |\n| sealed | permits | closed hierarchy |\n| permits | allowed subtypes | compile enforced |\n| non-sealed | open again | escape hatch |\n| exhaustive switch | all cases | sealed help |\n| accessor | x() | not getX |\n| equals/hash | components | generated |\n| implements | interfaces ok | multiple |\n| extends | Record only | no other class |\n| pattern switch | case Circle c | destructure |\n| DTO use | API payloads | great fit |\n| JPA entity | usually class | mutability |\n| reflection | RecordComponent | frameworks |\n| serialization | evolve carefully | compat |"
    }
  ]
}
